sc/V.py
sc/__init__.py
sc/flow_solver.py
sc/janitor.py
sc/random_field.py
sc/simulation.py
sc/transport_solver.py
PyDDC-1.2.6.dist-info/METADATA
PyDDC-1.2.6.dist-info/WHEEL
PyDDC-1.2.6.dist-info/top_level.txt
PyDDC-1.2.6.dist-info/RECORD
