Metadata-Version: 2.1
Name: PyDDC
Version: 1.2.6
Summary: Simulates density-driven convection of single phase CO2--brine mixture
Author: Sayan Sen, Scott K. Hansen
Requires-Python: >=3.11
Requires-Dist: CO2Br (==0.0.1)
Requires-Dist: numpy (>=1.26.4)
Requires-Dist: scipy (>=1.15.2)
Requires-Dist: matplotlib (>=3.6.2)
Requires-Dist: gstools (>=1.4.1)
Requires-Dist: numba (>=0.60.0)
Requires-Dist: tables (>=3.10.2)
Requires-Dist: tqdm (>=4.66.2)
Requires-Dist: h5py (>=3.7.0)
